js_enhanced_logging/__init__.py
js_enhanced_logging/custom_formatter.py
js_enhanced_logging/enhanced_logger.py
js_enhanced_logging-1.0.3.dist-info/METADATA
js_enhanced_logging-1.0.3.dist-info/WHEEL
js_enhanced_logging-1.0.3.dist-info/top_level.txt
js_enhanced_logging-1.0.3.dist-info/RECORD
