Metadata-Version: 2.1
Name: js-enhanced-logging
Version: 1.0.3
Summary: Python package for js_enhanced_logging
Requires-Dist: colorama
